{
  "projects": [
    {
      "id": 1,
      "title": "Consulting services to prepare Service and Business Plan for Amman BRT Feeder Buses Operations",
      "slug": "consulting-services-service-business-plan-amman-brt-feeder-buses",
      "card": {
        "thumbnail": "/our-projects/project-1/image-1.jpg",
        "location": "Jordan"
      },
      "heroImages": [
        "/our-projects/project-1/image-1.jpg",
        "/our-projects/project-1/image-2.jpg",
        "/our-projects/project-1/image-3.jpg"
      ],
      "sliderImages": [
        "/our-projects/project-1/image-1.jpg",
        "/our-projects/project-1/image-2.jpg",
        "/our-projects/project-1/image-3.jpg"
      ],
      "description": [
        "Conduct comprehensive traffic surveys in Amman to inform the development of a sustainable public transportation system.",
        "Main target of this survey campaign is to provide Excel sheet data containing five types of surveys that will be conducted inside Amman city boundaries:",
        "• Boarding/Alighting at Main Stops/In Terminal Passenger Survey.",
        "• Board Passenger Survey / In Vehicle Passenger Count.",
        "• OD Questionnaire Survey.",
        "• Manual Classified Counts / Using Video Camera.",
        "• White Taxi Ridership Survey."
      ],
      "details": {
        "sector": [],
        "location": "",
        "clients": ["Greater Amman Municipality", "Arabtech Jardaneh", "IDOM"],
        "periodsOfServices": "2021-2022"
      }
    },
    {
      "id": 2,
      "title": "Amaar Group Tower",
      "slug": "amaar-group-tower",
      "card": {
        "thumbnail": "/our-projects/thumbnail/project.png",
        "location": "UAE - Abu Dhabi"
      },
      "heroImage": "/our-projects/hero-img/project-hero-img.jpg",
      "sliderImages": [
        "/our-projects/slider/slider-1.jpg",
        "/our-projects/slider/slider-2.jpg",
        "/our-projects/slider/slider-3.jpg",
        "/our-projects/slider/slider-4.jpg"
      ],
      "description": [
        "Lorem Ipsum is simply dummy text of the printing and typesetting industry, used as placeholder content.",
        "This is where you can place a longer description for the Amaar Group Tower project."
      ],
      "details": {
        "sector": ["Residential", "Architecture & Design"],
        "location": "UAE - Abu Dhabi",
        "clients": ["Amaar Group"],
        "periodsOfServices": "2010-2014"
      }
    },
    {
      "id": 3,
      "title": "Amaar Group Tower",
      "slug": "amaar-group-tower",
      "card": {
        "thumbnail": "/our-projects/thumbnail/project.png",
        "location": "UAE - Abu Dhabi"
      },
      "heroImage": "/our-projects/hero-img/project-hero-img.jpg",
      "sliderImages": [
        "/our-projects/slider/slider-1.jpg",
        "/our-projects/slider/slider-2.jpg",
        "/our-projects/slider/slider-3.jpg",
        "/our-projects/slider/slider-4.jpg"
      ],
      "description": [
        "Lorem Ipsum is simply dummy text of the printing and typesetting industry, used as placeholder content.",
        "This is where you can place a longer description for the Amaar Group Tower project."
      ],
      "details": {
        "sector": ["Residential", "Architecture & Design"],
        "location": "UAE - Abu Dhabi",
        "clients": ["Amaar Group"],
        "periodsOfServices": "2010-2014"
      }
    },
    {
      "id": 4,
      "title": "Amaar Group Tower",
      "slug": "amaar-group-tower",
      "card": {
        "thumbnail": "/our-projects/thumbnail/project.png",
        "location": "UAE - Abu Dhabi"
      },
      "heroImage": "/our-projects/hero-img/project-hero-img.jpg",
      "sliderImages": [
        "/our-projects/slider/slider-1.jpg",
        "/our-projects/slider/slider-2.jpg",
        "/our-projects/slider/slider-3.jpg",
        "/our-projects/slider/slider-4.jpg"
      ],
      "description": [
        "Lorem Ipsum is simply dummy text of the printing and typesetting industry, used as placeholder content.",
        "This is where you can place a longer description for the Amaar Group Tower project."
      ],
      "details": {
        "sector": ["Residential", "Architecture & Design"],
        "location": "UAE - Abu Dhabi",
        "clients": ["Amaar Group"],
        "periodsOfServices": "2010-2014"
      }
    },
    {
      "id": 5,
      "title": "Amaar Group Tower",
      "slug": "amaar-group-tower",
      "card": {
        "thumbnail": "/our-projects/thumbnail/project.png",
        "location": "UAE - Abu Dhabi"
      },
      "heroImage": "/our-projects/hero-img/project-hero-img.jpg",
      "sliderImages": [
        "/our-projects/slider/slider-1.jpg",
        "/our-projects/slider/slider-2.jpg",
        "/our-projects/slider/slider-3.jpg",
        "/our-projects/slider/slider-4.jpg"
      ],
      "description": [
        "Lorem Ipsum is simply dummy text of the printing and typesetting industry, used as placeholder content.",
        "This is where you can place a longer description for the Amaar Group Tower project."
      ],
      "details": {
        "sector": ["Residential", "Architecture & Design"],
        "location": "UAE - Abu Dhabi",
        "clients": ["Amaar Group"],
        "periodsOfServices": "2010-2014"
      }
    },
    {
      "id": 6,
      "title": "Amaar Group Tower",
      "slug": "amaar-group-tower",
      "card": {
        "thumbnail": "/our-projects/thumbnail/project.png",
        "location": "UAE - Abu Dhabi"
      },
      "heroImage": "/our-projects/hero-img/project-hero-img.jpg",
      "sliderImages": [
        "/our-projects/slider/slider-1.jpg",
        "/our-projects/slider/slider-2.jpg",
        "/our-projects/slider/slider-3.jpg",
        "/our-projects/slider/slider-4.jpg"
      ],
      "description": [
        "Lorem Ipsum is simply dummy text of the printing and typesetting industry, used as placeholder content.",
        "This is where you can place a longer description for the Amaar Group Tower project."
      ],
      "details": {
        "sector": ["Residential", "Architecture & Design"],
        "location": "UAE - Abu Dhabi",
        "clients": ["Amaar Group"],
        "periodsOfServices": "2010-2014"
      }
    },
    {
      "id": 7,
      "title": "Amaar Group Tower",
      "slug": "amaar-group-tower",
      "card": {
        "thumbnail": "/our-projects/thumbnail/project.png",
        "location": "UAE - Abu Dhabi"
      },
      "heroImage": "/our-projects/hero-img/project-hero-img.jpg",
      "sliderImages": [
        "/our-projects/slider/slider-1.jpg",
        "/our-projects/slider/slider-2.jpg",
        "/our-projects/slider/slider-3.jpg",
        "/our-projects/slider/slider-4.jpg"
      ],
      "description": [
        "Lorem Ipsum is simply dummy text of the printing and typesetting industry, used as placeholder content.",
        "This is where you can place a longer description for the Amaar Group Tower project."
      ],
      "details": {
        "sector": ["Residential", "Architecture & Design"],
        "location": "UAE - Abu Dhabi",
        "clients": ["Amaar Group"],
        "periodsOfServices": "2010-2014"
      }
    },
    {
      "id": 8,
      "title": "Amaar Group Tower",
      "slug": "amaar-group-tower",
      "card": {
        "thumbnail": "/our-projects/thumbnail/project.png",
        "location": "UAE - Abu Dhabi"
      },
      "heroImage": "/our-projects/hero-img/project-hero-img.jpg",
      "sliderImages": [
        "/our-projects/slider/slider-1.jpg",
        "/our-projects/slider/slider-2.jpg",
        "/our-projects/slider/slider-3.jpg",
        "/our-projects/slider/slider-4.jpg"
      ],
      "description": [
        "Lorem Ipsum is simply dummy text of the printing and typesetting industry, used as placeholder content.",
        "This is where you can place a longer description for the Amaar Group Tower project."
      ],
      "details": {
        "sector": ["Residential", "Architecture & Design"],
        "location": "UAE - Abu Dhabi",
        "clients": ["Amaar Group"],
        "periodsOfServices": "2010-2014"
      }
    },
    {
      "id": 9,
      "title": "Amaar Group Tower",
      "slug": "amaar-group-tower",
      "card": {
        "thumbnail": "/our-projects/thumbnail/project.png",
        "location": "UAE - Abu Dhabi"
      },
      "heroImage": "/our-projects/hero-img/project-hero-img.jpg",
      "sliderImages": [
        "/our-projects/slider/slider-1.jpg",
        "/our-projects/slider/slider-2.jpg",
        "/our-projects/slider/slider-3.jpg",
        "/our-projects/slider/slider-4.jpg"
      ],
      "description": [
        "Lorem Ipsum is simply dummy text of the printing and typesetting industry, used as placeholder content.",
        "This is where you can place a longer description for the Amaar Group Tower project."
      ],
      "details": {
        "sector": ["Residential", "Architecture & Design"],
        "location": "UAE - Abu Dhabi",
        "clients": ["Amaar Group"],
        "periodsOfServices": "2010-2014"
      }
    },
    {
      "id": 10,
      "title": "Amaar Group Tower",
      "slug": "amaar-group-tower",
      "card": {
        "thumbnail": "/our-projects/thumbnail/project.png",
        "location": "UAE - Abu Dhabi"
      },
      "heroImage": "/our-projects/hero-img/project-hero-img.jpg",
      "sliderImages": [
        "/our-projects/slider/slider-1.jpg",
        "/our-projects/slider/slider-2.jpg",
        "/our-projects/slider/slider-3.jpg",
        "/our-projects/slider/slider-4.jpg"
      ],
      "description": [
        "Lorem Ipsum is simply dummy text of the printing and typesetting industry, used as placeholder content.",
        "This is where you can place a longer description for the Amaar Group Tower project."
      ],
      "details": {
        "sector": ["Residential", "Architecture & Design"],
        "location": "UAE - Abu Dhabi",
        "clients": ["Amaar Group"],
        "periodsOfServices": "2010-2014"
      }
    },
    {
      "id": 11,
      "title": "Amaar Group Tower",
      "slug": "amaar-group-tower",
      "card": {
        "thumbnail": "/our-projects/thumbnail/project.png",
        "location": "UAE - Abu Dhabi"
      },
      "heroImage": "/our-projects/hero-img/project-hero-img.jpg",
      "sliderImages": [
        "/our-projects/slider/slider-1.jpg",
        "/our-projects/slider/slider-2.jpg",
        "/our-projects/slider/slider-3.jpg",
        "/our-projects/slider/slider-4.jpg"
      ],
      "description": [
        "Lorem Ipsum is simply dummy text of the printing and typesetting industry, used as placeholder content.",
        "This is where you can place a longer description for the Amaar Group Tower project."
      ],
      "details": {
        "sector": ["Residential", "Architecture & Design"],
        "location": "UAE - Abu Dhabi",
        "clients": ["Amaar Group"],
        "periodsOfServices": "2010-2014"
      }
    },
    {
      "id": 12,
      "title": "Amaar Group Tower",
      "slug": "amaar-group-tower",
      "card": {
        "thumbnail": "/our-projects/thumbnail/project.png",
        "location": "UAE - Abu Dhabi"
      },
      "heroImage": "/our-projects/hero-img/project-hero-img.jpg",
      "sliderImages": [
        "/our-projects/slider/slider-1.jpg",
        "/our-projects/slider/slider-2.jpg",
        "/our-projects/slider/slider-3.jpg",
        "/our-projects/slider/slider-4.jpg"
      ],
      "description": [
        "Lorem Ipsum is simply dummy text of the printing and typesetting industry, used as placeholder content.",
        "This is where you can place a longer description for the Amaar Group Tower project."
      ],
      "details": {
        "sector": ["Residential", "Architecture & Design"],
        "location": "UAE - Abu Dhabi",
        "clients": ["Amaar Group"],
        "periodsOfServices": "2010-2014"
      }
    }
  ]
}
